blockly_runner/__init__.py
blockly_runner/constants.py
blockly_runner/exceptions.py
blockly_runner/typing.py
blockly_runner/utils.py
blockly_runner-0.1.4.dist-info/LICENSE
blockly_runner-0.1.4.dist-info/WHEEL
blockly_runner-0.1.4.dist-info/METADATA
blockly_runner-0.1.4.dist-info/RECORD
