Metadata-Version: 2.1
Name: blockly_runner
Version: 0.1.4
Summary: Run blockly workspaces directly, without the need to convert it to Python code.
Keywords: Blockly,Google Blockly,Interpertor
Author-email: Bankstore <tech@bankstore.fr>
Requires-Python: >=3.8
Classifier: Intended Audience :: Developers
Classifier: License :: OSI Approved :: MIT License
Classifier: Operating System :: Unix
Classifier: Operating System :: POSIX
Classifier: Operating System :: Microsoft :: Windows
Classifier: Programming Language :: Python
Classifier: Programming Language :: Python :: 3
Classifier: Programming Language :: Python :: 3 :: Only
Classifier: Programming Language :: Python :: 3.8
Classifier: Programming Language :: Python :: 3.9
Classifier: Programming Language :: Python :: 3.10
Project-URL: Home, https://github.com/bankstore-fr/python-blockly-runner/
